{
    "openapi": "3.0.0",
    "info": {
        "title": "API",
        "version": "1.0.0"
    },
    "paths": {
        "/api/v1/user": {
            "get": {
                "summary": "Get list of users",
                "operationId": "7e5b40495c8c742505e6042c37444fa8",
                "parameters": [
                    {
                        "name": "includeProduct",
                        "in": "query",
                        "description": "Include related products",
                        "required": false,
                        "schema": {
                            "type": "boolean"
                        }
                    }
                ],
                "responses": {
                    "200": {
                        "description": "Success"
                    },
                    "400": {
                        "description": "Bad Request"
                    }
                }
            }
        }
    }
}